prox_oss2/__init__.py
prox_oss2/api.py
prox_oss2/auth.py
prox_oss2/compat.py
prox_oss2/defaults.py
prox_oss2/exceptions.py
prox_oss2/http.py
prox_oss2/iterators.py
prox_oss2/models.py
prox_oss2/resumable.py
prox_oss2/task_queue.py
prox_oss2/utils.py
prox_oss2/xml_utils.py
prox_oss2-2.3.2.1.dist-info/DESCRIPTION.rst
prox_oss2-2.3.2.1.dist-info/METADATA
prox_oss2-2.3.2.1.dist-info/RECORD
prox_oss2-2.3.2.1.dist-info/WHEEL
prox_oss2-2.3.2.1.dist-info/metadata.json
prox_oss2-2.3.2.1.dist-info/top_level.txt
